CHANGES.txt
README.txt
bootstrap.py
buildout.cfg
setup.py
src/zope/__init__.py
src/zope.app.traversing.egg-info/PKG-INFO
src/zope.app.traversing.egg-info/SOURCES.txt
src/zope.app.traversing.egg-info/dependency_links.txt
src/zope.app.traversing.egg-info/namespace_packages.txt
src/zope.app.traversing.egg-info/not-zip-safe
src/zope.app.traversing.egg-info/top_level.txt
src/zope/app/__init__.py
src/zope/app/traversing/__init__.py
src/zope/app/traversing/adapters.py
src/zope/app/traversing/api.py
src/zope/app/traversing/interfaces.py
src/zope/app/traversing/namespace.py
src/zope/app/traversing/browser/__init__.py
src/zope/app/traversing/browser/absoluteurl.py
src/zope/app/traversing/browser/interfaces.py
